screen_html/__init__.py
screen_html/webdriver.py
screen_html-0.1.0.dist-info/LICENSE.txt
screen_html-0.1.0.dist-info/METADATA
screen_html-0.1.0.dist-info/WHEEL
screen_html-0.1.0.dist-info/top_level.txt
screen_html-0.1.0.dist-info/RECORD
