Metadata-Version: 2.1
Name: screen-html
Version: 0.1.0
Summary: This is a Python script that uses Playwright to render HTML and convert it into an image.
Home-page: https://github.com/Xpos587/screen-html
Author: Xpos587
License: MIT
Classifier: Programming Language :: Python :: 3
Classifier: License :: OSI Approved :: MIT License
Classifier: Operating System :: OS Independent
Requires-Python: >=3.7
License-File: LICENSE.txt
Requires-Dist: Jinja2
Requires-Dist: playwright
